pyaddepar/__init__.py
pyaddepar/addeparrequest.py
pyaddepar/flask_addepar.py
pyaddepar-0.12.0.dist-info/METADATA
pyaddepar-0.12.0.dist-info/WHEEL
pyaddepar-0.12.0.dist-info/RECORD
