Metadata-Version: 2.4
Name: pyaddepar
Version: 0.12.0
Summary: ...
Project-URL: repository, https://github.com/lobnek/pyaddepar
Author-email: Thomas Schmelzer <thomas.schmelzer@gmail.com>
Requires-Python: >=3.9
Requires-Dist: flask>=3.1.0
Requires-Dist: pandas>=2.2.3
Requires-Dist: requests>=2.32.3
